fast_skimage/Collection.py
fast_skimage/Image.py
fast_skimage/Image_tests.py
fast_skimage/__init__.py
fast_skimage/astronaut_noisy.py
fast_skimage/camera.py
fast_skimage/etretat.py
fast_skimage/nyc.py
fast_skimage/walking.py
fast_skimage/watermark.py
fast_skimage/zebra.py
fast_skimage-0.3.1.dist-info/LICENSE
fast_skimage-0.3.1.dist-info/METADATA
fast_skimage-0.3.1.dist-info/WHEEL
fast_skimage-0.3.1.dist-info/top_level.txt
fast_skimage-0.3.1.dist-info/RECORD
