Metadata-Version: 2.1
Name: fast-skimage
Version: 0.3.1
Summary: Fast and easy image processing using an Image class based on the scikit-image, numpy and matplotlib libraries.
Home-page: https://github.com/TortueSagace/fast_skimage
Author: Alexandre Le Mercier
Author-email: alexandre.le.mercier@ulb.be
License: MIT
Platform: UNKNOWN
Classifier: Intended Audience :: Developers
Classifier: License :: OSI Approved :: MIT License
Classifier: Programming Language :: Python
Classifier: Programming Language :: Python :: 3
Classifier: Programming Language :: Python :: 3.6
Classifier: Programming Language :: Python :: 3.7
Classifier: Programming Language :: Python :: 3.8
Classifier: Programming Language :: Python :: 3.9
Classifier: Operating System :: OS Independent
Requires-Dist: PyWavelets
Requires-Dist: matplotlib
Requires-Dist: numpy
Requires-Dist: scikit-image
Requires-Dist: scikit-learn
Requires-Dist: tqdm
